jaxspd/__init__.py
jaxspd/gpu.py
jaxspd/jit.py
jaxspd/optimizations.py
jaxspd/profiling.py
jaxspd/utils.py
jaxspd-0.1.4.dist-info/licenses/LICENSE
jaxspd-0.1.4.dist-info/METADATA
jaxspd-0.1.4.dist-info/WHEEL
jaxspd-0.1.4.dist-info/top_level.txt
jaxspd-0.1.4.dist-info/RECORD
