Metadata-Version: 2.4
Name: jaxspd
Version: 0.1.4
Summary: JAX Speed Optimizations
Home-page: https://github.com/jaxcontrib/jaxspd
Author: JAX Contributor
Author-email: jaxdev@example.com
Classifier: Development Status :: 3 - Alpha
Classifier: Intended Audience :: Science/Research
Classifier: Operating System :: OS Independent
Classifier: Programming Language :: Python :: 3
Classifier: Programming Language :: Python :: 3.8
Classifier: Programming Language :: Python :: 3.9
Classifier: Programming Language :: Python :: 3.10
Classifier: Programming Language :: Python :: 3.11
Classifier: Topic :: Scientific/Engineering :: Artificial Intelligence
Requires-Python: >=3.8
License-File: LICENSE
Requires-Dist: jax>=0.4.13
Requires-Dist: jaxlib>=0.4.13
Requires-Dist: numpy>=1.20.0
Provides-Extra: gpu
Requires-Dist: cuda-python; extra == "gpu"
Dynamic: author
Dynamic: author-email
Dynamic: classifier
Dynamic: description
Dynamic: description-content-type
Dynamic: home-page
Dynamic: license-file
Dynamic: provides-extra
Dynamic: requires-dist
Dynamic: requires-python
Dynamic: summary
